capylang/__init__.py
capylang/aiml/__init__.py
capylang/base/__init__.py
capylang/capi/__init__.py
capylang/color/__init__.py
capylang/core/__init__.py
capylang/date/__init__.py
capylang/decorators/__init__.py
capylang/http/__init__.py
capylang/string/__init__.py
capylang/terminal/__init__.py
capylang-2.2.0.dist-info/WHEEL
capylang-2.2.0.dist-info/METADATA
capylang-2.2.0.dist-info/RECORD
