Metadata-Version: 2.1
Name: capylang
Version: 2.2.0
Summary: Python's little programming language.
Author: Anistick Team
Author-email: all@anistick.com
Maintainer: Kia Kazemi
Maintainer-email: kia@anistick.com
Requires-Python: >=3.8.0
Classifier: Development Status :: 5 - Production/Stable
Classifier: License :: OSI Approved :: MIT License
Classifier: Operating System :: OS Independent
Classifier: Programming Language :: Python :: 3
Classifier: Programming Language :: Python :: 3.10
Classifier: Programming Language :: Python :: 3.8
Classifier: Programming Language :: Python :: 3.9
Requires-Dist: colorama (>=0.4.5,<0.5.0)
Requires-Dist: numpy (>=1.22.2,<2.0.0)
Requires-Dist: pygame (>=2.1.2,<3.0.0)
Requires-Dist: replit (>=3.2.4,<4.0.0)
Requires-Dist: requests (>=2.28.1,<3.0.0)
